{
  "project_info": {
    "project_number": "912632814531",
    "firebase_url": "https://smart3dviewer-33615.firebaseio.com",
    "project_id": "smart3dviewer-33615",
    "storage_bucket": "smart3dviewer-33615.appspot.com"
  },
  "client": [
    {
      "client_info": {
        "mobilesdk_app_id": "1:912632814531:android:e02a613c7bab16b8",
        "android_client_info": {
          "package_name": "com.smart3dviewer"
        }
      },
      "oauth_client": [
        {
          "client_id": "912632814531-abnoasnqjngkkm7jv0okvqb2ale943a8.apps.googleusercontent.com",
          "client_type": 1,
          "android_info": {
            "package_name": "com.smart3dviewer",
            "certificate_hash": "2e6358ba94f4060a8f8060ea6986e6e830280389"
          }
        },
        {
          "client_id": "912632814531-j06u11s0i36etefmsb6bbvt9tuitrepg.apps.googleusercontent.com",
          "client_type": 3
        }
      ],
      "api_key": [
        {
          "current_key": "AIzaSyDZAp71TZtj43g8UiB6TXJ9encLzgKWgBU"
        }
      ],
      "services": {
        "analytics_service": {
          "status": 1
        },
        "appinvite_service": {
          "status": 2,
          "other_platform_oauth_client": [
            {
              "client_id": "912632814531-j06u11s0i36etefmsb6bbvt9tuitrepg.apps.googleusercontent.com",
              "client_type": 3
            }
          ]
        },
        "ads_service": {
          "status": 2
        }
      }
    }
  ],
  "configuration_version": "1"
}